ffta/__init__.py
ffta/__version__.py
ffta/analyze_pixel.py
ffta/line.py
ffta/pixel.py
ffta/_legacy_functions/__init__.py
ffta/_legacy_functions/analyze.py
ffta/acquisition/__init__.py
ffta/acquisition/generate_chirp.py
ffta/acquisition/polling.py
ffta/analysis/__init__.py
ffta/analysis/create_movie.py
ffta/analysis/dist_cluster.py
ffta/analysis/fft.py
ffta/analysis/filtering.py
ffta/analysis/gmode_utils.py
ffta/analysis/mask_utils.py
ffta/analysis/proc_utils.py
ffta/analysis/select_pixel.py
ffta/analysis/svd.py
ffta/analysis/svd_utils.py
ffta/analysis/test_pixel.py
ffta/gkpfm/__init__.py
ffta/gkpfm/gkline.py
ffta/gkpfm/gkpixel.py
ffta/gkpfm/gkprocess.py
ffta/gkpfm/gmode_simple.py
ffta/gkpfm/load_excitation.py
ffta/gkpfm/transfer_func.py
ffta/hdf_utils/__init__.py
ffta/hdf_utils/analyze_h5.py
ffta/hdf_utils/hdf_utils.py
ffta/hdf_utils/plot_tfp.py
ffta/hdf_utils/process.py
ffta/load/__init__.py
ffta/load/get_utils.py
ffta/load/gl_ibw.py
ffta/load/load_commands.py
ffta/load/load_hdf.py
ffta/load/load_ringdown.py
ffta/nfmd/NFMD.py
ffta/nfmd/NFMDPixel.py
ffta/nfmd/__init__.py
ffta/nfmd/models.py
ffta/pixel_utils/__init__.py
ffta/pixel_utils/badpixels.py
ffta/pixel_utils/dwavelet.py
ffta/pixel_utils/fitting.py
ffta/pixel_utils/load.py
ffta/pixel_utils/noise.py
ffta/pixel_utils/parab.py
ffta/pixel_utils/peakdetect.py
ffta/pixel_utils/tfp_calc.py
ffta/simulation/__init__.py
ffta/simulation/broadband_drive.py
ffta/simulation/calibration_curve.py
ffta/simulation/cantilever.py
ffta/simulation/electric_drive.py
ffta/simulation/impulse.py
ffta/simulation/mechanical_drive.py
ffta/simulation/mechanical_drive_simple.py
ffta/simulation/utils/__init__.py
ffta/simulation/utils/excitation.py
ffta/simulation/utils/load.py
tests/__init__.py
tests/test_ffta.py
FFTA-0.3.5.1.dist-info/LICENSE.txt
FFTA-0.3.5.1.dist-info/METADATA
FFTA-0.3.5.1.dist-info/WHEEL
FFTA-0.3.5.1.dist-info/top_level.txt
FFTA-0.3.5.1.dist-info/RECORD
