Metadata-Version: 2.1
Name: FFTA
Version: 0.3.5.1
Summary: Fast Free Transient Analysis
Home-page: https://github.com/rajgiriUW/ffta/
Author: Rajiv Giridharagopal
Author-email: rgiri@uw.edu
License: MIT
License-File: LICENSE.txt
Requires-Dist: numpy (>=1.20.0)
Requires-Dist: scipy (>=1.4.1)
Requires-Dist: igor2 (>=0.5.2)
Requires-Dist: numexpr (>=2.7.1)
Requires-Dist: pyUSID (>=0.0.10)
Requires-Dist: pywavelets (>=1.1.1)
Requires-Dist: sidpy (>=0.0.5)
Requires-Dist: pandas (>=1.1.0)
Requires-Dist: BGlib (>=0.0.3)
Requires-Dist: torch (>=1.6.0)
Requires-Dist: scikit-image (>=0.19.2)
